coinmarketcap/__init__.py
coinmarketcap/core.py
coinmarketcap/types/__init__.py
coinmarketcap/types/quote_factory.py
coinmarketcap/types/token_info_factory.py
coinmarketcap/types/token_state_factory.py
coinmarketcap/v1/cryptocurrency/map.py
coinmarketcap/v1/cryptocurrency/listings/common.py
coinmarketcap/v1/cryptocurrency/listings/latest.py
coinmarketcap/v1/key/__init__.py
coinmarketcap/v1/key/info.py
coinmarketcap/v2/cryptocurrency/quotes/historical.py
coinmarketcap/v3/cryptocurrency/quotes/historical_v3.py
coinmarketcap/v3/fear_and_greed/historical.py
byteforge_coinmarketcap-2.0.dist-info/METADATA
byteforge_coinmarketcap-2.0.dist-info/WHEEL
byteforge_coinmarketcap-2.0.dist-info/licenses/LICENSE
byteforge_coinmarketcap-2.0.dist-info/RECORD
