Metadata-Version: 2.4
Name: byteforge-coinmarketcap
Version: 2.0
Summary: Python SDK for the coinmarketcap.com API.
Project-URL: Homepage, https://github.com/jmazzahacks/byteforge-coinmarketcap/
Project-URL: Issues, https://github.com/jmazzahacks/byteforge-coinmarketcap/issues
Author: Jason Byteforge
License:                              Apache License
License-File: LICENSE
Keywords: API,BTC,Bitcoin,ETH,Ethereum,LTC,Litecoin,Ripple,XRP,coinmarketcap,cryptocurrency
Classifier: License :: OSI Approved :: MIT License
Classifier: Operating System :: OS Independent
Classifier: Programming Language :: Python :: 3
Requires-Python: >=3.8
Requires-Dist: byteforge-crypto-commons
Requires-Dist: python-dateutil
Requires-Dist: requests
Requires-Dist: requests-cache
Requires-Dist: requests-ratelimiter
